facelandmarks/__init__.py
facelandmarks/config.py
facelandmarks/cropping.py
facelandmarks/face_dataset.py
facelandmarks/face_landmarking_model.py
facelandmarks/landmarks_utils.py
facelandmarks/preprocessing.py
facelandmarks/training.py
facelandmarks-0.1.0.dist-info/LICENCE
facelandmarks-0.1.0.dist-info/METADATA
facelandmarks-0.1.0.dist-info/WHEEL
facelandmarks-0.1.0.dist-info/top_level.txt
facelandmarks-0.1.0.dist-info/RECORD
